{
    "digest": "2d7d3126b4f539a5c747b7bed497626b",
    "modeling_results": {
        "XGBClassifier": {
            "accuracy": {
                "train": 1.0,
                "test": 0.9695286195286196
            },
            "feature_importances": [
                [
                    "quantity",
                    0.248778834939003
                ],
                [
                    "waterpoint_type",
                    0.15510912239551544
                ],
                [
                    "scheme_name",
                    0.10097765177488327
                ],
                [
                    "funder",
                    0.0832909420132637
                ],
                [
                    "installer",
                    0.04362717270851135
                ],
                [
                    "extraction_type",
                    0.03986992686986923
                ],
                [
                    "amount_tsh",
                    0.03169858455657959
                ],
                [
                    "region_code",
                    0.030217299237847328
                ],
                [
                    "payment_type",
                    0.028295544907450676
                ],
                [
                    "source",
                    0.026408884674310684
                ],
                [
                    "pump_age",
                    0.02593371830880642
                ],
                [
                    "longitude",
                    0.021508214995265007
                ],
                [
                    "basin",
                    0.021200772374868393
                ],
                [
                    "district_code",
                    0.02031674049794674
                ],
                [
                    "latitude",
                    0.01826709881424904
                ],
                [
                    "public_meeting",
                    0.017914211377501488
                ],
                [
                    "gps_height",
                    0.016972651705145836
                ],
                [
                    "permit",
                    0.016208358108997345
                ],
                [
                    "scheme_management",
                    0.016150202602148056
                ],
                [
                    "population",
                    0.015838589519262314
                ],
                [
                    "management",
                    0.011399045586585999
                ],
                [
                    "water_quality",
                    0.010016482323408127
                ]
            ]
        }
    },
    "seed": 42
}